Workbook

Sheet Instrucciones
A1: Josefine Auto — Calculadora de rentabilidad
A3: Cómo usarla
A4: 1. Celdas con fondo AMARILLO y texto AZUL = datos que tú escribes. Todo lo demás se calcula solo.
A5: 2. 'Reglas': tus criterios mínimos de compra. Ajústalos una vez y valen para todos los coches.
A6: 3. 'Compra': antes de ofertar por un coche, rellena sus números. Te dice si COMPRAR o NO y el precio máximo que puedes pagar.
A7: 4. 'Consignación': calcula lo que ganas vendiendo un coche ajeno a comisión.
A8: 5. 'Mapa de precios': anota anuncios comparables. Te da el precio realista de venta de cada modelo.
A9: 6. 'Registro': anota cada operación cerrada. Te da tu margen medio, días de venta y capital acumulado.
A11: Los valores que vienen escritos son EJEMPLOS orientativos. Sustitúyelos por cifras reales.
A12: Costes de traspaso, revisado y tasas en Panamá: verifica importes vigentes con la ATTT / municipio.
A13: Moneda: dólares (USD).

Sheet Reglas
A1: Reglas de compra (tus criterios mínimos)
A3: Regla | B3: Valor | C3: Nota
A4: Ganancia neta mínima por coche | B4: 600 | C4: Ejemplo basado en tu margen histórico ($500–1.500).
A5: Margen mínimo sobre precio de venta | B5: 0.12 | C5: Ejemplo: 12%.
A6: Días máximos esperados para vender | B6: 45 | C6: Objetivo: rotar en menos de 45 días.
A7: Colchón para imprevistos (% del precio de compra) | B7: 0.08 | C7: Reserva para averías no detectadas.
A8: Capital disponible total | B8: 5000 | C8: Dato del usuario: menos de $5.000.
A9: Reserva de capital que nunca se invierte | B9: 500 | C9: Para no quedarte sin liquidez.
A11: Precio máximo de compra según capital | B11: =B8-B9

Sheet Compra
A1: Análisis de compra — un coche
A3: Datos del coche
A4: Coche (marca, modelo, año, km) | B4: EJEMPLO: Mazda3 2010 · 150.000 km
A5: Precio de compra (oferta) | B5: 3200
A6: Precio de venta esperado (realista) | B6: 4900
A7: Inspección en taller | B7: 60
A8: Reparaciones / mantenimiento | B8: 300
A9: Detallado / estética | B9: 100
A10: Traspaso, revisado y papeles | B10: 150
A11: Publicidad (anuncios pagados) | B11: 30
A12: Otros gastos | B12: 0
A13: Días estimados hasta vender | B13: 30
A15: Resultados
A16: Colchón para imprevistos | B16: =B5*Reglas!$B$7
A17: Coste total (compra + gastos + colchón) | B17: =SUM(B5,B7:B12)+B16
A18: Ganancia neta estimada | B18: =B6-B17
A19: Margen sobre venta | B19: =IF(B6=0,0,B18/B6)
A20: Retorno sobre lo invertido | B20: =IF(B17=0,0,B18/B17)
A21: Retorno anualizado (aprox.) | B21: =IF(B13=0,0,B20*365/B13)
A22: Ganancia por día de stock | B22: =IF(B13=0,0,B18/B13)
A23: Precio MÁXIMO de compra para cumplir reglas | B23: =MIN(B6-SUM(B7:B12)-Reglas!$B$4, B6*(1-Reglas!$B$5)-SUM(B7:B12))/(1+Reglas!$B$7)
A24: ¿Cabe en tu capital? | B24: =IF(B17<=Reglas!$B$11,"SÍ","NO — excede capital")
A25: DECISIÓN | B25: =IF(AND(B18>=Reglas!$B$4,B19>=Reglas!$B$5,B13<=Reglas!$B$6,B17<=Reglas!$B$11),"COMPRAR","NO COMPRAR")
A27: Regla de oro: si el vendedor no acepta un precio igual o menor al 'Precio MÁXIMO de compra', se pasa al siguiente coche.

Sheet Consignación
A1: Venta a comisión (consignación)
A3: Coche | B3: EJEMPLO: Nissan 350Z 2008 modificado
A4: Precio de venta acordado con el dueño | B4: 14000
A5: Comisión (%) | B5: 0.05
A6: Comisión mínima fija | B6: 500
A7: Gastos tuyos (fotos, detallado, anuncios) | B7: 150
A8: Días estimados hasta vender | B8: 45
A10: Comisión cobrada | B10: =MAX(B4*B5,B6)
A11: Ganancia neta | B11: =B10-B7
A12: Ganancia por día | B12: =IF(B8=0,0,B11/B8)
A13: Lo que recibe el dueño | B13: =B4-B10
A15: Ejemplo orientativo: comisión entre 3% y 8% con un mínimo fijo. Firma siempre un contrato de consignación por escrito.

Sheet Registro
A1: Registro de operaciones
A3: Coche | B3: Tipo | C3: Fecha compra | D3: Precio compra | E3: Gastos totales | F3: Fecha venta | G3: Precio venta | H3: Días en stock | I3: Ganancia neta | J3: Margen | K3: Canal de venta | M3: Resumen
A4: Ejemplo: Toyota Yaris 2011 | B4: Compra propia | C4: 46305 | D4: 3300 | E4: 600 | F4: 46331 | G4: 4800 | H4: =IF(OR(C4="",F4=""),"",F4-C4) | I4: =IF(G4="","",IF(B4="Consignación",G4-E4,G4-D4-E4)) | J4: =IF(OR(G4="",G4=0),"",IF(B4="Consignación",I4/D4,I4/G4)) | K4: Instagram | M4: Operaciones cerradas | N4: =COUNT(I4:I53)
H5: =IF(OR(C5="",F5=""),"",F5-C5) | I5: =IF(G5="","",IF(B5="Consignación",G5-E5,G5-D5-E5)) | J5: =IF(OR(G5="",G5=0),"",IF(B5="Consignación",I5/D5,I5/G5)) | M5: Ganancia total | N5: =SUM(I4:I53)
H6: =IF(OR(C6="",F6=""),"",F6-C6) | I6: =IF(G6="","",IF(B6="Consignación",G6-E6,G6-D6-E6)) | J6: =IF(OR(G6="",G6=0),"",IF(B6="Consignación",I6/D6,I6/G6)) | M6: Ganancia media | N6: =IF(N4=0,0,N5/N4)
H7: =IF(OR(C7="",F7=""),"",F7-C7) | I7: =IF(G7="","",IF(B7="Consignación",G7-E7,G7-D7-E7)) | J7: =IF(OR(G7="",G7=0),"",IF(B7="Consignación",I7/D7,I7/G7)) | M7: Días medios en stock | N7: =IF(COUNT(H4:H53)=0,0,AVERAGE(H4:H53))
H8: =IF(OR(C8="",F8=""),"",F8-C8) | I8: =IF(G8="","",IF(B8="Consignación",G8-E8,G8-D8-E8)) | J8: =IF(OR(G8="",G8=0),"",IF(B8="Consignación",I8/D8,I8/G8)) | M8: Margen medio | N8: =IF(COUNT(J4:J53)=0,0,AVERAGE(J4:J53))
H9: =IF(OR(C9="",F9=""),"",F9-C9) | I9: =IF(G9="","",IF(B9="Consignación",G9-E9,G9-D9-E9)) | J9: =IF(OR(G9="",G9=0),"",IF(B9="Consignación",I9/D9,I9/G9)) | M9: Capital actual (inicial + ganancias) | N9: =Reglas!B8+N5
H10: =IF(OR(C10="",F10=""),"",F10-C10) | I10: =IF(G10="","",IF(B10="Consignación",G10-E10,G10-D10-E10)) | J10: =IF(OR(G10="",G10=0),"",IF(B10="Consignación",I10/D10,I10/G10))
H11: =IF(OR(C11="",F11=""),"",F11-C11) | I11: =IF(G11="","",IF(B11="Consignación",G11-E11,G11-D11-E11)) | J11: =IF(OR(G11="",G11=0),"",IF(B11="Consignación",I11/D11,I11/G11))
H12: =IF(OR(C12="",F12=""),"",F12-C12) | I12: =IF(G12="","",IF(B12="Consignación",G12-E12,G12-D12-E12)) | J12: =IF(OR(G12="",G12=0),"",IF(B12="Consignación",I12/D12,I12/G12))
H13: =IF(OR(C13="",F13=""),"",F13-C13) | I13: =IF(G13="","",IF(B13="Consignación",G13-E13,G13-D13-E13)) | J13: =IF(OR(G13="",G13=0),"",IF(B13="Consignación",I13/D13,I13/G13))
H14: =IF(OR(C14="",F14=""),"",F14-C14) | I14: =IF(G14="","",IF(B14="Consignación",G14-E14,G14-D14-E14)) | J14: =IF(OR(G14="",G14=0),"",IF(B14="Consignación",I14/D14,I14/G14))
H15: =IF(OR(C15="",F15=""),"",F15-C15) | I15: =IF(G15="","",IF(B15="Consignación",G15-E15,G15-D15-E15)) | J15: =IF(OR(G15="",G15=0),"",IF(B15="Consignación",I15/D15,I15/G15))
H16: =IF(OR(C16="",F16=""),"",F16-C16) | I16: =IF(G16="","",IF(B16="Consignación",G16-E16,G16-D16-E16)) | J16: =IF(OR(G16="",G16=0),"",IF(B16="Consignación",I16/D16,I16/G16))
H17: =IF(OR(C17="",F17=""),"",F17-C17) | I17: =IF(G17="","",IF(B17="Consignación",G17-E17,G17-D17-E17)) | J17: =IF(OR(G17="",G17=0),"",IF(B17="Consignación",I17/D17,I17/G17))
H18: =IF(OR(C18="",F18=""),"",F18-C18) | I18: =IF(G18="","",IF(B18="Consignación",G18-E18,G18-D18-E18)) | J18: =IF(OR(G18="",G18=0),"",IF(B18="Consignación",I18/D18,I18/G18))
H19: =IF(OR(C19="",F19=""),"",F19-C19) | I19: =IF(G19="","",IF(B19="Consignación",G19-E19,G19-D19-E19)) | J19: =IF(OR(G19="",G19=0),"",IF(B19="Consignación",I19/D19,I19/G19))
H20: =IF(OR(C20="",F20=""),"",F20-C20) | I20: =IF(G20="","",IF(B20="Consignación",G20-E20,G20-D20-E20)) | J20: =IF(OR(G20="",G20=0),"",IF(B20="Consignación",I20/D20,I20/G20))
H21: =IF(OR(C21="",F21=""),"",F21-C21) | I21: =IF(G21="","",IF(B21="Consignación",G21-E21,G21-D21-E21)) | J21: =IF(OR(G21="",G21=0),"",IF(B21="Consignación",I21/D21,I21/G21))
... H53: =IF(OR(C53="",F53=""),"",F53-C53) | I53: =IF(G53="","",IF(B53="Consignación",G53-E53,G53-D53-E53)) | J53: =IF(OR(G53="",G53=0),"",IF(B53="Consignación",I53/D53,I53/G53))

Sheet Mapa de precios
A1: Mapa de precios: anuncios comparables (Ciudad de Panamá)
A2: Anota cada anuncio que veas de tus modelos objetivo. El resumen te dice el precio típico pedido de cada modelo.
A4: Modelo | B4: Año | C4: Km | D4: Transmisión | E4: Precio pedido | F4: Fuente / enlace | G4: Fecha | H4: Notas | J4: Modelo objetivo | K4: Anuncios | L4: Precio medio | M4: Mínimo | N4: Máximo | O4: Venta realista (-10%)
A5: Mazda3 | B5: 2010 | C5: 150000 | D5: Automática | E5: 5200 | F5: Encuentra24 | G5: 46298 | H5: EJEMPLO: borra esta fila | J5: Mazda3 | K5: =IF(J5="","",COUNTIF($A$5:$A$204,J5)) | L5: =IF(OR(J5="",K5=0),"",AVERAGEIF($A$5:$A$204,J5,$E$5:$E$204)) | M5: =IF(OR(J5="",K5=0),"",_xlfn.MINIFS($E$5:$E$204,$A$5:$A$204,J5)) | N5: =IF(OR(J5="",K5=0),"",_xlfn.MAXIFS($E$5:$E$204,$A$5:$A$204,J5)) | O5: =IF(L5="","",L5*(1-$K$17))
J6: Toyota Yaris | K6: =IF(J6="","",COUNTIF($A$5:$A$204,J6)) | L6: =IF(OR(J6="",K6=0),"",AVERAGEIF($A$5:$A$204,J6,$E$5:$E$204)) | M6: =IF(OR(J6="",K6=0),"",_xlfn.MINIFS($E$5:$E$204,$A$5:$A$204,J6)) | N6: =IF(OR(J6="",K6=0),"",_xlfn.MAXIFS($E$5:$E$204,$A$5:$A$204,J6)) | O6: =IF(L6="","",L6*(1-$K$17))
J7: Toyota Corolla | K7: =IF(J7="","",COUNTIF($A$5:$A$204,J7)) | L7: =IF(OR(J7="",K7=0),"",AVERAGEIF($A$5:$A$204,J7,$E$5:$E$204)) | M7: =IF(OR(J7="",K7=0),"",_xlfn.MINIFS($E$5:$E$204,$A$5:$A$204,J7)) | N7: =IF(OR(J7="",K7=0),"",_xlfn.MAXIFS($E$5:$E$204,$A$5:$A$204,J7)) | O7: =IF(L7="","",L7*(1-$K$17))
J8: Honda Civic | K8: =IF(J8="","",COUNTIF($A$5:$A$204,J8)) | L8: =IF(OR(J8="",K8=0),"",AVERAGEIF($A$5:$A$204,J8,$E$5:$E$204)) | M8: =IF(OR(J8="",K8=0),"",_xlfn.MINIFS($E$5:$E$204,$A$5:$A$204,J8)) | N8: =IF(OR(J8="",K8=0),"",_xlfn.MAXIFS($E$5:$E$204,$A$5:$A$204,J8)) | O8: =IF(L8="","",L8*(1-$K$17))
J9: Honda Fit | K9: =IF(J9="","",COUNTIF($A$5:$A$204,J9)) | L9: =IF(OR(J9="",K9=0),"",AVERAGEIF($A$5:$A$204,J9,$E$5:$E$204)) | M9: =IF(OR(J9="",K9=0),"",_xlfn.MINIFS($E$5:$E$204,$A$5:$A$204,J9)) | N9: =IF(OR(J9="",K9=0),"",_xlfn.MAXIFS($E$5:$E$204,$A$5:$A$204,J9)) | O9: =IF(L9="","",L9*(1-$K$17))
K10: =IF(J10="","",COUNTIF($A$5:$A$204,J10)) | L10: =IF(OR(J10="",K10=0),"",AVERAGEIF($A$5:$A$204,J10,$E$5:$E$204)) | M10: =IF(OR(J10="",K10=0),"",_xlfn.MINIFS($E$5:$E$204,$A$5:$A$204,J10)) | N10: =IF(OR(J10="",K10=0),"",_xlfn.MAXIFS($E$5:$E$204,$A$5:$A$204,J10)) | O10: =IF(L10="","",L10*(1-$K$17))
K11: =IF(J11="","",COUNTIF($A$5:$A$204,J11)) | L11: =IF(OR(J11="",K11=0),"",AVERAGEIF($A$5:$A$204,J11,$E$5:$E$204)) | M11: =IF(OR(J11="",K11=0),"",_xlfn.MINIFS($E$5:$E$204,$A$5:$A$204,J11)) | N11: =IF(OR(J11="",K11=0),"",_xlfn.MAXIFS($E$5:$E$204,$A$5:$A$204,J11)) | O11: =IF(L11="","",L11*(1-$K$17))
K12: =IF(J12="","",COUNTIF($A$5:$A$204,J12)) | L12: =IF(OR(J12="",K12=0),"",AVERAGEIF($A$5:$A$204,J12,$E$5:$E$204)) | M12: =IF(OR(J12="",K12=0),"",_xlfn.MINIFS($E$5:$E$204,$A$5:$A$204,J12)) | N12: =IF(OR(J12="",K12=0),"",_xlfn.MAXIFS($E$5:$E$204,$A$5:$A$204,J12)) | O12: =IF(L12="","",L12*(1-$K$17))
K13: =IF(J13="","",COUNTIF($A$5:$A$204,J13)) | L13: =IF(OR(J13="",K13=0),"",AVERAGEIF($A$5:$A$204,J13,$E$5:$E$204)) | M13: =IF(OR(J13="",K13=0),"",_xlfn.MINIFS($E$5:$E$204,$A$5:$A$204,J13)) | N13: =IF(OR(J13="",K13=0),"",_xlfn.MAXIFS($E$5:$E$204,$A$5:$A$204,J13)) | O13: =IF(L13="","",L13*(1-$K$17))
K14: =IF(J14="","",COUNTIF($A$5:$A$204,J14)) | L14: =IF(OR(J14="",K14=0),"",AVERAGEIF($A$5:$A$204,J14,$E$5:$E$204)) | M14: =IF(OR(J14="",K14=0),"",_xlfn.MINIFS($E$5:$E$204,$A$5:$A$204,J14)) | N14: =IF(OR(J14="",K14=0),"",_xlfn.MAXIFS($E$5:$E$204,$A$5:$A$204,J14)) | O14: =IF(L14="","",L14*(1-$K$17))
J17: Descuento típico sobre precio pedido | K17: 0.1
J18: Usa 'Venta realista' como 'Precio de venta esperado' en la hoja Compra. Compara siempre el mismo año aproximado y km.
